huggingface/__init__.py
huggingface-0.0.1.dist-info/METADATA
huggingface-0.0.1.dist-info/WHEEL
huggingface-0.0.1.dist-info/top_level.txt
huggingface-0.0.1.dist-info/RECORD
