Metadata-Version: 1.1
Name: huggingface
Version: 0.0.1
Summary:  HuggingFace is a single library comprising the main HuggingFace libraries.
Home-page: https://github.com/huggingface/huggingface
Author: HuggingFace Inc.
Author-email: thomas@huggingface.co
License: Apache 2.0
Download-URL: https://github.com/huggingface/huggingface/tags
Platform: UNKNOWN
Classifier: Development Status :: 5 - Production/Stable
Classifier: Intended Audience :: Developers
Classifier: Intended Audience :: Education
Classifier: Intended Audience :: Science/Research
Classifier: License :: OSI Approved :: Apache Software License
Classifier: Operating System :: OS Independent
Classifier: Programming Language :: Python :: 3
Classifier: Programming Language :: Python :: 3.6
Classifier: Programming Language :: Python :: 3.7
Classifier: Topic :: Scientific/Engineering :: Artificial Intelligence
